{
    "area_of_operations": "East Borca",
    "concept": "The Seeker",
    "cult": "Chroniclers",
    "culture": "Borca",
    "image_name": "icons-chroniclers-iridium.jpg",
    "image_url": "https://img2.storyblok.com/1492x0/filters:quality(90)/f/72501/4000x4000/8653b4c1e2/icons-chroniclers-iridium.jpg",
    "last_seen": "2595",
    "name": "Iridium",
    "rank": "Needle",
    "source": [
        "Primal Punk"
    ],
    "source_url": "https://degenesis.com/world/icons/chroniclers/iridium",
    "summary": "The adopted name of a Needle who betrayed the Central Cluster after crossing the Reaper\u2019s Blow. Founder of the Needle Tower Iridium.",
    "url_name": "iridium"
}