{
    "area_of_operations": "Purgare, Syracuse",
    "concept": "The Visionary",
    "cult": "Neolibyans",
    "culture": "Africa",
    "image_name": "icons-neolibyans-sarahali.jpg",
    "image_url": "https://img2.storyblok.com/1492x0/filters:quality(90)/f/72501/2000x2000/7e090a4610/icons-neolibyans-sarahali.jpg",
    "last_seen": "2596",
    "name": "Sarahali",
    "rank": "Consul",
    "source": [
        "Primal Punk"
    ],
    "source_url": "https://degenesis.com/world/icons/neolibyans/sarahali",
    "summary": "Consul of Bedain. Ousted the locals and transformed Syracuse into a mighty ship wrecking harbor where Scrappers from all over the world go to find work.",
    "url_name": "sarahali"
}